ecs_container_exporter/__init__.py
ecs_container_exporter/cpu_metrics.py
ecs_container_exporter/io_metrics.py
ecs_container_exporter/main.py
ecs_container_exporter/memory_metrics.py
ecs_container_exporter/network_metrics.py
ecs_container_exporter/utils.py
ecs_container_exporter-2.3.0.dist-info/LICENSE
ecs_container_exporter-2.3.0.dist-info/METADATA
ecs_container_exporter-2.3.0.dist-info/WHEEL
ecs_container_exporter-2.3.0.dist-info/entry_points.txt
ecs_container_exporter-2.3.0.dist-info/top_level.txt
ecs_container_exporter-2.3.0.dist-info/RECORD
