Metadata-Version: 2.1
Name: ecs-container-exporter
Version: 2.3.0
Summary: Prometheus exporter for AWS ECS Task and Container Metrics
Home-page: https://github.com/Spaced-Out/ecs-container-exporter
Author: Raghu Udiyar
Author-email: raghusiddarth@gmail.com
License: MIT License
Platform: UNKNOWN
Classifier: Environment :: Console
Classifier: Intended Audience :: Developers
Classifier: Programming Language :: Python
Classifier: Programming Language :: Python :: 3.6
Classifier: Programming Language :: Python :: 3.7
License-File: LICENSE
Requires-Dist: setuptools (>=36.0.0)
Requires-Dist: Click (==7.0)
Requires-Dist: prometheus-client (==0.7.1)
Requires-Dist: requests (==2.22.0)
Requires-Dist: datadog (==0.39.0)
